salahai/__init__.py
salahai-1.2.0.dist-info/METADATA
salahai-1.2.0.dist-info/WHEEL
salahai-1.2.0.dist-info/top_level.txt
salahai-1.2.0.dist-info/RECORD
