Metadata-Version: 2.4
Name: salahai
Version: 1.2.0
Summary: SalahAi - ذكاء اصطناعي ذكي
Home-page: https://facebook.com/cap.salah.hemdan
Author: Salah Hemdan
Author-email: salah1hemdaan@gmail.com
Classifier: Programming Language :: Python :: 3
Classifier: License :: OSI Approved :: MIT License
Classifier: Operating System :: OS Independent
Requires-Python: >=3.6
Requires-Dist: requests
Dynamic: author
Dynamic: author-email
Dynamic: classifier
Dynamic: description
Dynamic: description-content-type
Dynamic: home-page
Dynamic: requires-dist
Dynamic: requires-python
Dynamic: summary
